fastapi_mail/__init__.py
fastapi_mail/config.py
fastapi_mail/connection.py
fastapi_mail/email_utils/__init__.py
fastapi_mail/email_utils/email_check.py
fastapi_mail/errors.py
fastapi_mail/fastmail.py
fastapi_mail/msg.py
fastapi_mail/py.typed
fastapi_mail/schemas.py
fastapi_mail-1.5.9.dist-info/METADATA
fastapi_mail-1.5.9.dist-info/WHEEL
fastapi_mail-1.5.9.dist-info/licenses/LICENSE
fastapi_mail-1.5.9.dist-info/RECORD
