Metadata-Version: 2.4
Name: fastapi-mail
Version: 1.5.9
Summary: Simple lightweight mail library for FastApi
License: MIT
License-File: LICENSE
Author: Sabuhi Shukurov
Author-email: sabuhi.shukurov@gmail.com
Requires-Python: >=3.10.0,<4.0.0
Classifier: License :: OSI Approved :: MIT License
Classifier: Programming Language :: Python :: 3
Classifier: Programming Language :: Python :: 3.10
Classifier: Programming Language :: Python :: 3.11
Classifier: Programming Language :: Python :: 3.12
Classifier: Programming Language :: Python :: 3.13
Classifier: Programming Language :: Python :: 3.14
Provides-Extra: httpx
Provides-Extra: redis
Requires-Dist: aiosmtplib (>=5.0.0,<6.0.0)
Requires-Dist: blinker (>=1.9.0,<2.0.0)
Requires-Dist: cryptography (>=46.0.3,<47.0.0)
Requires-Dist: email-validator (>=2.3.0,<3.0.0)
Requires-Dist: httpx (>=0.28.1,<0.29.0) ; extra == "httpx"
Requires-Dist: jinja2 (>=3.1.6,<4.0.0)
Requires-Dist: pydantic (>=2.12.5,<3.0.0)
Requires-Dist: pydantic-settings (>=2.6.1,<3.0.0)
Requires-Dist: redis (>=6.4.0,<7.0.0) ; extra == "redis"
Requires-Dist: regex (>=2025.11.3,<2026.0.0)
Requires-Dist: starlette (>=0.24,<1.0)
Requires-Dist: typing-extensions (>=4.15.0,<5.0.0)
Project-URL: Homepage, https://github.com/sabuhish/fastapi-mail
Project-URL: Repository, https://github.com/sabuhish/fastapi-mail
